attrs_serde/__init__.py
attrs_serde/__version__.py
attrs_serde/attrs_serde.py
attrs_serde-0.2.4.dist-info/LICENSE
attrs_serde-0.2.4.dist-info/WHEEL
attrs_serde-0.2.4.dist-info/METADATA
attrs_serde-0.2.4.dist-info/RECORD
