Metadata-Version: 2.1
Name: attrs-serde
Version: 0.2.4
Summary: A serialization addon for attrs
Home-page: https://github.com/jondot/attrs-serde
License: MIT
Keywords: attrs,serialization,dict,data,nested,functional
Author: Dotan Nahum
Author-email: jondotan@gmail.com
Classifier: License :: OSI Approved :: MIT License
Classifier: Programming Language :: Python :: 2
Classifier: Programming Language :: Python :: 2.7
Classifier: Programming Language :: Python :: 3
Classifier: Programming Language :: Python :: 3.4
Classifier: Programming Language :: Python :: 3.5
Classifier: Programming Language :: Python :: 3.6
Classifier: Programming Language :: Python :: 3.7
Provides-Extra: lint
Requires-Dist: attrs (>=19.1,<20.0)
Requires-Dist: cytoolz (>=0.9.0,<0.10.0)
Requires-Dist: toolz (>=0.9.0,<0.10.0)
Project-URL: Documentation, https://github.com/jondot/attrs-serde
Project-URL: Repository, https://github.com/jondot/attrs-serde
